image_to_ascii/__init__.py
image_to_ascii/image_to_ascii.py
image_to_ascii_pyaoponto-0.3.dist-info/LICENSE.txt
image_to_ascii_pyaoponto-0.3.dist-info/METADATA
image_to_ascii_pyaoponto-0.3.dist-info/WHEEL
image_to_ascii_pyaoponto-0.3.dist-info/top_level.txt
image_to_ascii_pyaoponto-0.3.dist-info/RECORD
