Metadata-Version: 2.1
Name: image-to-ascii-pyaoponto
Version: 0.3
Summary: A Python module to transform image to ascii art
Home-page: https://github.com/estevaofon/image-to-ascii-pyaoponto
Author: Python Direto ao Ponto
Author-email: pyaoponto@gmail.com
License: MIT
Keywords: ascii,image,art
Platform: UNKNOWN
Classifier: Programming Language :: Python :: 3
Classifier: License :: OSI Approved :: MIT License
Classifier: Operating System :: OS Independent
Requires-Python: >=3.6
License-File: LICENSE.txt
Requires-Dist: Pillow
